pyssht/CMakeLists.txt
pyssht/SSHT_Python_Documentation.md
pyssht/__init__.py
pyssht/cpyssht.cpython-39-aarch64-linux-gnu.so
pyssht/cpyssht.pyx
pyssht/ducc_demo.py
pyssht/ducc_interface.cpython-39-aarch64-linux-gnu.so
pyssht/ducc_interface.pyx
pyssht/exceptions.py
pyssht/parameters.py
pyssht/pyssht_demo_0.py
pyssht/pyssht_demo_1.py
pyssht/pyssht_demo_2.py
pyssht/pyssht_demo_3.py
pyssht/pyssht_demo_4.py
pyssht/pyssht_demo_5.py
pyssht/pyssht_demo_6.py
pyssht/pyssht_demo_7.py
pyssht-1.5.3.dist-info/METADATA
pyssht-1.5.3.dist-info/WHEEL
pyssht-1.5.3.dist-info/RECORD
pyssht-1.5.3.dist-info/licenses/LICENSE
