Metadata-Version: 2.4
Name: pyssht
Version: 1.5.3
Summary: Fast spin spherical transforms
Keywords: numerical transforms,signal processing,science
Author: J. D. McEwen, C. R. G. Wallis, M. Buttner, B. Leistedt, Y. Wiaux
License-Expression: GPL-3.0-or-later
Project-URL: Homepage, http://astro-informatics.github.io/ssht/
Project-URL: Repository, http://github.com/astro-informatics/ssht.git
Project-URL: Issues, http://github.com/astro-informatics/ssht/issues
Requires-Python: >=3.8
Requires-Dist: numpy
Requires-Dist: scipy
Provides-Extra: ducc0
Requires-Dist: ducc0>=0.18; extra == "ducc0"
